_isda.cp37-win_amd64.pyd
isda/__init__.py
isda/badday.c
isda/bsearch.c
isda/buscache.c
isda/busday.c
isda/cashflow.c
isda/cds.c
isda/cdsbootstrap.c
isda/cdsone.c
isda/cerror.c
isda/cfileio.c
isda/cfinanci.cpp
isda/cmemory.c
isda/contingentleg.c
isda/convert.c
isda/cx.c
isda/cxbsearch.c
isda/cxdatelist.c
isda/cxzerocurve.c
isda/date_sup.c
isda/dateadj.c
isda/dateconv.c
isda/datelist.c
isda/defaulted.c
isda/dtlist.c
isda/example.c
isda/feeleg.c
isda/fltrate.c
isda/gtozc.c
isda/imm.py
isda/interpc.c
isda/isda.cpp
isda/isda.py
isda/isda_wrap.cxx
isda/ldate.c
isda/lintrp1.c
isda/lprintf.c
isda/lscanf.c
isda/main.c
isda/rtbrent.c
isda/schedule.c
isda/streamcf.c
isda/strutil.c
isda/stub.c
isda/tcurve.c
isda/timeline.c
isda/version.c
isda/yearfrac.c
isda/zcall.c
isda/zcswap.c
isda/zcswdate.c
isda/zcswutil.c
isda/zerocurve.c
isda/zr2coup.c
isda/zr2fwd.c
isda/tests/TestBBGEd.py
isda/tests/TestCDSW.py
isda/tests/TestCdsPricer-Metlife.py
isda/tests/TestCdsPricer.py
isda/tests/TestCdsPricerExcludeInterestRateTenorDates.py
isda/tests/TestCdsPricerIndex.py
isda/tests/TestCdsPricerOriginal.py
isda/tests/TestCdsPricerRR.py
isda/tests/TestCdsPricerRoll.py
isda/tests/TestDiscountRate.py
isda/tests/TestPaymentSchedule.py
isda/tests/TestSCBRecon.py
isda/tests/TestSpreadFromUpfront.py
isda/tests/TestSwaption.py
isda/tests/TestUpfrontFee.py
isda/tests/TestUpfrontFee2.py
isda/tests/TestUpfrontFee3.py
isda/tests/TestUpfrontFee4.py
isda/tests/TestUpfrontFee5.py
isda/tests/TestUpfrontFee6.py
isda/tests/__init__.py
isda/tests/simpletst.py
isda-1.0.24.dist-info/LICENSE
isda-1.0.24.dist-info/LICENSE.txt
isda-1.0.24.dist-info/METADATA
isda-1.0.24.dist-info/WHEEL
isda-1.0.24.dist-info/top_level.txt
isda-1.0.24.dist-info/RECORD
